onion_props/__init__.py
onion_props/onion_props.py
onion_props-0.2.4.dist-info/DESCRIPTION.rst
onion_props-0.2.4.dist-info/METADATA
onion_props-0.2.4.dist-info/RECORD
onion_props-0.2.4.dist-info/WHEEL
onion_props-0.2.4.dist-info/metadata.json
onion_props-0.2.4.dist-info/top_level.txt
