Metadata-Version: 2.0
Name: onion-props
Version: 0.2.4
Summary: An elegant hierarchical (or "onioned") properties parser
Home-page: https://github.com/eternali/onion_props
Author: Conrad Heidebrecht
Author-email: conrad.heidebrecht@gmail.com
License: UNKNOWN
Keywords: properties java parser
Platform: any
Classifier: Development Status :: 4 - Beta
Classifier: Intended Audience :: Developers
Classifier: License :: OSI Approved :: GNU General Public License v3 or later (GPLv3+)
Classifier: Programming Language :: Python :: 2
Classifier: Programming Language :: Python :: 3
Requires-Dist: datetime
